<?xml version="1.0" encoding="UTF-8"?>
<!DOCTYPE mapper PUBLIC "-//mybatis.org//DTD Mapper 3.0//EN" "http://mybatis.org/dtd/mybatis-3-mapper.dtd">
<mapper namespace="com.odm.oa.mapper.PositionMapper">
  <resultMap id="BaseResultMap" type="com.odm.oa.entity.Position">
    <!--
      WARNING - @mbg.generated
      This element is automatically generated by MyBatis Generator, do not modify.
      This element was generated on Mon Apr 09 17:59:38 CST 2018.
    -->
    <id column="id" jdbcType="BIGINT" property="id" />
    <result column="position_name" jdbcType="VARCHAR" property="positionName" />
    <result column="rank" jdbcType="CHAR" property="rank" />
    <result column="remark" jdbcType="VARCHAR" property="remark" />
    <result column="del_flg" jdbcType="BIT" property="delFlg" />
    <result column="version" jdbcType="INTEGER" property="version" />
    <result column="create_id" jdbcType="VARCHAR" property="createId" />
    <result column="create_time" jdbcType="DATE" property="createTime" />
    <result column="update_id" jdbcType="VARCHAR" property="updateId" />
    <result column="update_time" jdbcType="DATE" property="updateTime" />
  </resultMap>
  <delete id="deleteByPrimaryKey" parameterType="java.lang.Long">
    <!--
      WARNING - @mbg.generated
      This element is automatically generated by MyBatis Generator, do not modify.
      This element was generated on Mon Apr 09 17:59:38 CST 2018.
    -->
    delete from position
    where id = #{id,jdbcType=BIGINT}
  </delete>
  <insert id="insert" parameterType="com.odm.oa.entity.Position">
    <!--
      WARNING - @mbg.generated
      This element is automatically generated by MyBatis Generator, do not modify.
      This element was generated on Mon Apr 09 17:59:38 CST 2018.
    -->
    insert into position (id, position_name, rank, 
      remark, del_flg, version, 
      create_id, create_time, update_id, 
      update_time)
    values (#{id,jdbcType=BIGINT}, #{positionName,jdbcType=VARCHAR}, #{rank,jdbcType=CHAR}, 
      #{remark,jdbcType=VARCHAR}, #{delFlg,jdbcType=BIT}, #{version,jdbcType=INTEGER}, 
      #{createId,jdbcType=VARCHAR}, #{createTime,jdbcType=DATE}, #{updateId,jdbcType=VARCHAR}, 
      #{updateTime,jdbcType=DATE})
  </insert>
  <update id="updateByPrimaryKey" parameterType="com.odm.oa.entity.Position">
    <!--
      WARNING - @mbg.generated
      This element is automatically generated by MyBatis Generator, do not modify.
      This element was generated on Mon Apr 09 17:59:38 CST 2018.
    -->
    update position
    set position_name = #{positionName,jdbcType=VARCHAR},
      rank = #{rank,jdbcType=CHAR},
      remark = #{remark,jdbcType=VARCHAR},
      del_flg = #{delFlg,jdbcType=BIT},
      version = #{version,jdbcType=INTEGER},
      create_id = #{createId,jdbcType=VARCHAR},
      create_time = #{createTime,jdbcType=DATE},
      update_id = #{updateId,jdbcType=VARCHAR},
      update_time = #{updateTime,jdbcType=DATE}
    where id = #{id,jdbcType=BIGINT}
  </update>
  <select id="selectByPrimaryKey" parameterType="java.lang.Long" resultMap="BaseResultMap">
    <!--
      WARNING - @mbg.generated
      This element is automatically generated by MyBatis Generator, do not modify.
      This element was generated on Mon Apr 09 17:59:38 CST 2018.
    -->
    select id, position_name, rank, remark, del_flg, version, create_id, create_time, 
    update_id, update_time
    from position
    where id = #{id,jdbcType=BIGINT}
  </select>
  <select id="selectAll" resultMap="BaseResultMap">
    <!--
      WARNING - @mbg.generated
      This element is automatically generated by MyBatis Generator, do not modify.
      This element was generated on Mon Apr 09 17:59:38 CST 2018.
    -->
    select id, position_name, rank, remark, del_flg, version, create_id, create_time, 
    update_id, update_time
    from position where del_flg='0'
  </select>
  <select id="pageList" resultMap="BaseResultMap" parameterType="com.odm.oa.model.request.PaginationBase">
    select id, position_name,rank,remark, del_flg, version, create_id, create_time, update_id, update_time
    from POSITION where del_flg = 0
  </select>
  <select id="getByName" parameterType="java.lang.String" resultType="int">
    select count(1)
    from POSITION where position_name = #{name,jdbcType=VARCHAR}
  </select>
</mapper>